{
  "db_name": "PostgreSQL",
  "query": "\n                        SELECT * FROM categories\n                        WHERE category_id = $1 AND user_id = $2\n                    ",
  "describe": {
    "columns": [
      {
        "ordinal": 0,
        "name": "category_id",
        "type_info": "Int4"
      },
      {
        "ordinal": 1,
        "name": "user_id",
        "type_info": "Uuid"
      },
      {
        "ordinal": 2,
        "name": "created_at",
        "type_info": "Timestamptz"
      },
      {
        "ordinal": 3,
        "name": "category_name",
        "type_info": "Varchar"
      },
      {
        "ordinal": 4,
        "name": "description",
        "type_info": "Text"
      },
      {
        "ordinal": 5,
        "name": "updated_at",
        "type_info": "Timestamptz"
      },
      {
        "ordinal": 6,
        "name": "is_default",
        "type_info": "Bool"
      }
    ],
    "parameters": {
      "Left": [
        "Int4",
        "Uuid"
      ]
    },
    "nullable": [
      false,
      false,
      false,
      false,
      false,
      false,
      false
    ]
  },
  "hash": "8cd47179ef00cf134ebf537e311d3628e2267e44c62ce611bfe33cc0f35a7ffd"
}
